Workbook

Sheet Planilha1
B12: (CAPITAL DE GIRO)
B13: CAIXA | C13: =Planilha3!J7 -> 1250
B14: POUPANÇA | C14: =Planilha3!J8 -> 550
B15: INVESTIMENTO | C15: =Planilha3!J9 -> 780
B16: SALDO | C16: =SUM(C13:C15) -> 2580
B19: REGRA 50/30/20
B20: SALARIO | D20: 5000
B21: Necessidades essenciais | C21: 0.5 | D21: =D20*C21 -> 2500
B22: Desejos | C22: 0.3 | D22: =D20*C22 -> 1500
B23: Recomendação investir | C23: 0.2 | D23: =D20*C23 -> 1000
B26: PROPOSTA | F26: =D29 -> 0.0108 | G26: =D23 -> 1000
B27: PERFIL | D27: Conservador | F27: ANOS | G27: RESULTADO
B28: Quanto valor vai investir? | D28: =D23 -> 1000 | F28: 2 | G28: =FV($D$29,$F$28*12,D28*-1) -> 27230.864
B29: Rendimento mensal | D29: 0.0108 | F29: 5 | G29: =FV($D$29,$F$29*12,$D$28*-1) -> 83804.019
B30: Quantos anos? | D30: 2 | F30: 10 | G30: =FV($D$29,$F$30*12,$D$28*-1) -> 243457.67
B32: SIMULAÇÃO | G32: RESULTADO
B33: PATRIMONIO ACUMULADO | G33: =FV(D29,D30*12,D28*-1) -> 27230.864
B34: DIVIENDENDOS MENSAL | G34: =G33*D29 -> 294.09333
B37: TIPOS | C37: % | D37: Dividendo
B38: PAPEL | C38: =VLOOKUP($D$27&"-"&B38,Planilha3!A:D,4,FALSE) -> 0.3 | D38: =C38*$D$28 -> 300
B39: TIJOLO | C39: =VLOOKUP($D$27&"-"&B39,Planilha3!A:D,4,FALSE) -> 0.3 | D39: =C39*$D$28 -> 300
B40: HÍBRIDOS | C40: =VLOOKUP($D$27&"-"&B40,Planilha3!A:D,4,FALSE) -> 0.1 | D40: =C40*$D$28 -> 100
B41: FOFs | C41: =VLOOKUP($D$27&"-"&B41,Planilha3!A:D,4,FALSE) -> 0.1 | D41: =C41*$D$28 -> 100
B42: DESENVOLVIMENTO | C42: =VLOOKUP($D$27&"-"&B42,Planilha3!A:D,4,FALSE) -> 0.1 | D42: =C42*$D$28 -> 100
B43: HOTELARIAS | C43: =VLOOKUP($D$27&"-"&B43,Planilha3!A:D,4,FALSE) -> 0.1 | D43: =C43*$D$28 -> 100
B44: TOTAL | C44: =SUM(C38:C43) -> 1 | D44: =SUM(D38:D43) -> 1000

Sheet Planilha3
A2: CHAVES | B2: PERFIL | C2: TIPOS | D2: %
A3: =$B$3&"-"&C3 -> Conservador-PAPEL | B3: Conservador | C3: PAPEL | D3: 0.3 | I3: Moderado-HÍBRIDOS | J3: =VLOOKUP(I3,A:D,4,FALSE) -> 0.15
A4: =$B$3&"-"&C4 -> Conservador-TIJOLO | B4: Conservador | C4: TIJOLO | D4: 0.3
A5: =$B$3&"-"&C5 -> Conservador-HÍBRIDOS | B5: Conservador | C5: HÍBRIDOS | D5: 0.1
A6: =$B$3&"-"&C6 -> Conservador-FOFs | B6: Conservador | C6: FOFs | D6: 0.1 | I6: (CAPITAL DE GIRO)
A7: =$B$3&"-"&C7 -> Conservador-DESENVOLVIMENTO | B7: Conservador | C7: DESENVOLVIMENTO | D7: 0.1 | I7: CAIXA | J7: 1250
A8: =B8&"-"&C8 -> Conservador-HOTELARIAS | B8: Conservador | C8: HOTELARIAS | D8: 0.1 | I8: POUPANÇA | J8: 550
A9: =B9&"-"&C9 -> Moderado-PAPEL | B9: Moderado | C9: PAPEL | D9: 0.25 | I9: INVESTIMENTO | J9: 780
A10: =B10&"-"&C10 -> Moderado-TIJOLO | B10: Moderado | C10: TIJOLO | D10: 0.25 | I10: SALDO | J10: =SUM(J7:J9) -> 2580
A11: =B11&"-"&C11 -> Moderado-HÍBRIDOS | B11: Moderado | C11: HÍBRIDOS | D11: 0.15
A12: =B12&"-"&C12 -> Moderado-FOFs | B12: Moderado | C12: FOFs | D12: 0.15
A13: =B13&"-"&C13 -> Moderado-DESENVOLVIMENTO | B13: Moderado | C13: DESENVOLVIMENTO | D13: 0.1
A14: =B14&"-"&C14 -> Moderado-HOTELARIAS | B14: Moderado | C14: HOTELARIAS | D14: 0.1
A15: =B15&"-"&C15 -> Arrojado-PAPEL | B15: Arrojado | C15: PAPEL | D15: 0.4
A16: =B16&"-"&C16 -> Arrojado-TIJOLO | B16: Arrojado | C16: TIJOLO | D16: 0.4
A17: =B17&"-"&C17 -> Arrojado-HÍBRIDOS | B17: Arrojado | C17: HÍBRIDOS | D17: 0.1
A18: =B18&"-"&C18 -> Arrojado-FOFs | B18: Arrojado | C18: FOFs | D18: 0.05
A19: =B19&"-"&C19 -> Arrojado-DESENVOLVIMENTO | B19: Arrojado | C19: DESENVOLVIMENTO | D19: 0.05
A20: =B20&"-"&C20 -> Arrojado-HOTELARIAS | B20: Arrojado | C20: HOTELARIAS | D20: 0
